Full_adder/Full_adder.v
module full_adder(
    input a,
    input b,
    input cin,
    output sum,
    output cout
);

wire sum1;

assign sum1 = a ^ b;

// Sum is xor_gate

assign sum = sum1 ^ cin;

wire carry1;
wire carry2;

assign carry1 = a & b;

// carry is and_gate

assign carry2 = sum1 & cin;

assign cout = carry1 | carry2;

// cout is or_gate

endmodule

Full_adder/Full_adder_tb.v
module full_adder_tb;

    reg a;
    reg b;
    reg cin;
    wire sum;
    wire cout;

full_adder uut (
    .a(a),
    .b(b),
    .cin(cin),
    .sum(sum),
    .cout(cout)
);

initial begin
    $dumpfile("dump.vcd");
    $dumpvars(0, full_adder_tb);

    $display ("A B cin | sum cout");

    a = 0; b = 0; cin = 0; #10;
    $display("%b %b %b | %b %b", a, b, cin, sum, cout);

    a = 0; b = 0; cin = 1; #10;
    $display("%b %b %b | %b %b", a, b, cin, sum, cout);

    a = 0; b = 1; cin = 0; #10;
    $display("%b %b %b | %b %b", a, b, cin, sum, cout);

    a = 0; b = 1; cin = 1; #10;
    $display("%b %b %b | %b %b", a, b, cin, sum, cout);

    a = 1; b = 0; cin = 0; #10;
    $display("%b %b %b | %b %b", a, b, cin, sum, cout);

    a = 1; b = 0; cin = 1; #10;
    $display("%b %b %b | %b %b", a, b, cin, sum, cout);

    a = 1; b = 1; cin = 0; #10;
    $display("%b %b %b | %b %b", a, b, cin, sum, cout);

    a = 1; b = 1; cin = 1; #10;
    $display("%b %b %b | %b %b", a, b, cin, sum, cout);

    $finish;

end 

endmodule

Full_adder/dump.vcd
$date
	Fri Jul 10 19:19:33 2026
$end
$version
	Icarus Verilog
$end
$timescale
	1s
$end
$scope module full_adder_tb $end
$var wire 1 ! sum $end
$var wire 1 " cout $end
$var reg 1 # a $end
$var reg 1 $ b $end
$var reg 1 % cin $end
$scope module uut $end
$var wire 1 # a $end
$var wire 1 $ b $end
$var wire 1 & carry1 $end
$var wire 1 ' carry2 $end
$var wire 1 % cin $end
$var wire 1 " cout $end
$var wire 1 ! sum $end
$var wire 1 ( sum1 $end
$upscope $end
$upscope $end
$enddefinitions $end
$comment Show the parameter values. $end
$dumpall
$end
#0
$dumpvars
0(
0'
0&
0%
0$
0#
0"
0!
$end
#10
1!
1%
#20
1(
0%
1$
#30
1"
0!
1'
1%
#40
0$
1#
#50
0"
1!
0'
0%
#60
0!
1"
0(
1&
1$
#70
1!
1%
